{
  "required": true,
  "package": "cc.thonly.reverie_dreams.mixin",
  "compatibilityLevel": "JAVA_21",
  "mixins": [
    "BedBlockMixin",
    "EntityMixin",
    "ExampleMixin",
    "GuiElementBuilderMixin",
    "ItemStackMixin",
    "LevelSummaryMixin",
    "LivingEntityMixin",
    "PlayerEntityMixin",
    "RegistryLoaderMixin",
    "VillagerEntityMixin",
    "WorldMixin",
    "accessor.IAbstractBlockSettingsAccessor",
    "accessor.IComponentMapBuilderAccessor",
    "accessor.EntityAccessor",
    "accessor.ItemEntityAccessor",
    "accessor.ItemSettingsAccessor",
    "accessor.LivingEntityAccessor",
    "accessor.PlayerEntityAccessor",
    "accessor.ResourceAccessor",
    "accessor.VillagerEntityAccessor",
    "accessor.WoodTypeAccessor",
    "compat.PolymerCommonUtilsMixin",
    "compat.PolymerItemGroupContentAddS2CPayloadMixin",
    "patches.DefaultRPBuilderMixin",
    "patches.PolymerBlockUtilsMixin",
    "patches.ResourcePackManagerMixin",
    "registry.SimpleRegistryMixin",
    "server.MinecraftServerMixin",
    "server.ReloadableRegistriesMixin",
    "server.IServerAdvancementLoaderAccessor",
    "server.ServerPlayerEntityMixin",
    "server.ServerPlayNetworkHandlerMixin",
    "server.ServerWorldMixin"
  ],
  "injectors": {
    "defaultRequire": 1
  },
  "client": [
    "IntegratedServerLoaderMixin",
    "client.AbstractBlockMixin",
    "client.AbstractSoundInstanceAccessor",
    "client.BakedModelManagerMixin",
    "client.MinecraftClientMixin",
    "client.NoteBlockMixin",
    "patches.PolymerResourcePackMixin"
  ]
}